README.rst
setup.py
Flask_PaperTrail.egg-info/PKG-INFO
Flask_PaperTrail.egg-info/SOURCES.txt
Flask_PaperTrail.egg-info/dependency_links.txt
Flask_PaperTrail.egg-info/requires.txt
Flask_PaperTrail.egg-info/top_level.txt
flask_papertrail/__init__.py
flask_papertrail/core.py