Metadata-Version: 1.1
Name: Flask-PaperTrail
Version: 0.0.3
Summary: Adds PaperTrail logging to your Flask application
Home-page: https://github.com/cuonglm/flask_papertrail
Author: Cuong Manh Le
Author-email: cuong.manhle.vn@gmail.com
License: BSD
Keywords: flask,log
Platform: UNKNOWN
Classifier: Environment :: Web Environment
Classifier: Intended Audience :: Developers
Classifier: License :: OSI Approved :: BSD License
Classifier: Operating System :: OS Independent
Classifier: Programming Language :: Python
Classifier: Topic :: Internet :: WWW/HTTP :: Dynamic Content
Classifier: Topic :: Software Development :: Libraries :: Python Modules
